<?xml version="1.0" encoding="utf-8" ?>
<dwsync>
<file name="index.php" server="ftp.smartloan.lk/public_html/" local="131933052138859888" remote="131932854000000000" Dst="0" />
<file name="business_loan_apply.php" server="ftp.smartloan.lk/public_html/" local="131932528771477718" remote="131932330800000000" Dst="0" />
<file name="business_loan_wizard.php" server="ftp.smartloan.lk/public_html/" local="131972440729529797" remote="131972270400000000" Dst="0" />
<file name="footer.php" server="ftp.smartloan.lk/public_html/" local="131933030626318975" remote="131932832400000000" Dst="0" />
<file name="property_loan_apply.php" server="ftp.smartloan.lk/public_html/" local="131932528861717597" remote="131932330800000000" Dst="0" />
<file name="head.php" server="ftp.smartloan.lk/public_html/" local="131972334485443403" remote="131960866800000000" Dst="0" />
<file name="personal_loan_wizard.php" server="ftp.smartloan.lk/public_html/" local="131972468186084451" remote="131972270400000000" Dst="0" />
<file name="property_loan_wizard.php" server="ftp.smartloan.lk/public_html/" local="131930936248246759" remote="131930752200000000" Dst="0" />
<file name="second_loan_apply.php" server="ftp.smartloan.lk/public_html/" local="131930950047186278" remote="131930752200000000" Dst="0" />
<file name="condition.php" server="ftp.smartloan.lk/public_html/" local="131933049448430728" remote="131932851000000000" Dst="0" />
<file name="test_lable.php" server="ftp.smartloan.lk/public_html/" local="131852786660000000" remote="131930752200000000" Dst="0" />
<file name="welcome_message.php" server="ftp.smartloan.lk/public_html/" local="131732397460000000" remote="131930752200000000" Dst="0" />
</dwsync>